trobz_agent/.agent.py.un~
trobz_agent/__init__.py
trobz_agent/agent.py
trobz_agent-1.0.3.dist-info/licenses/LICENSE
trobz_agent-1.0.3.dist-info/WHEEL
trobz_agent-1.0.3.dist-info/entry_points.txt
trobz_agent-1.0.3.dist-info/METADATA
trobz_agent-1.0.3.dist-info/RECORD
