Metadata-Version: 2.4
Name: trobz-agent
Version: 1.0.3
Summary: Run an AI agent
Author: Hai Lang
Author-email: Hai Lang <hailn@trobz.com>
License-Expression: AGPL-3.0
License-File: LICENSE
Requires-Dist: typer>=0.19.2
Requires-Dist: uv~=0.7.12 ; extra == 'build'
Requires-Python: >=3.10
Project-URL: Repository, https://github.com/trobz/agent.py
Provides-Extra: build
